{
  "version": 2,
  "dependencies": {
    "net8.0": {
      "Microsoft.Data.Sqlite": {
        "type": "Direct",
        "requested": "[10.0.0, )",
        "resolved": "10.0.0",
        "contentHash": "I/azQ5WjwoLvSlTyDydkhARPSjYJN8jkXRjR5D92OeyTLbTrQ1K93rgf6XU+HYWHZA6lBI9SUOfl69OqEHb4ow==",
        "dependencies": {
          "Microsoft.Data.Sqlite.Core": "10.0.0",
          "SQLitePCLRaw.bundle_e_sqlite3": "2.1.11",
          "SQLitePCLRaw.core": "2.1.11"
        }
      },
      "SqlKata": {
        "type": "Direct",
        "requested": "[4.0.1, )",
        "resolved": "4.0.1",
        "contentHash": "uGGSjc5tHMQCTy17EZxXr74ty4P79rjtuiPWT2VsZQ8v+K6uoLaTyW050ezU3VRBmaL00b5+x0+6OfjA3l9USA=="
      },
      "SqlKata.Execution": {
        "type": "Direct",
        "requested": "[4.0.1, )",
        "resolved": "4.0.1",
        "contentHash": "pFQg2Jn6sKtrDJyQBAYFvJQr7o5uB1rlUtOqxmLYkfPeAx6Nx8MFU1WyqE6LzYkVG6fKH2sNgG9VXl6EOKavPA==",
        "dependencies": {
          "Humanizer.Core": "2.8.26",
          "SqlKata": "4.0.1",
          "dapper": "2.0.123"
        }
      },
      "Dapper": {
        "type": "Transitive",
        "resolved": "2.0.123",
        "contentHash": "RDFF4rBLLmbpi6pwkY7q/M6UXHRJEOerplDGE5jwEkP/JGJnBauAClYavNKJPW1yOTWRPIyfj4is3EaJxQXILQ=="
      },
      "Humanizer.Core": {
        "type": "Transitive",
        "resolved": "2.8.26",
        "contentHash": "OiKusGL20vby4uDEswj2IgkdchC1yQ6rwbIkZDVBPIR6al2b7n3pC91elBul9q33KaBgRKhbZH3+2Ur4fnWx2A=="
      },
      "Microsoft.Data.Sqlite.Core": {
        "type": "Transitive",
        "resolved": "10.0.0",
        "contentHash": "wPKG/Ym6tSMCo06UOZXzVfeFGzawnOZrTba/R3PfK+RhNuNELZ9I7nFns4WGTtv2kKlrlmmErgJ+kgTXHaNdHg==",
        "dependencies": {
          "SQLitePCLRaw.core": "2.1.11"
        }
      },
      "Microsoft.Extensions.DependencyInjection.Abstractions": {
        "type": "Transitive",
        "resolved": "10.0.0",
        "contentHash": "L3AdmZ1WOK4XXT5YFPEwyt0ep6l8lGIPs7F5OOBZc77Zqeo01Of7XXICy47628sdVl0v/owxYJTe86DTgFwKCA=="
      },
      "Microsoft.Extensions.Logging.Abstractions": {
        "type": "Transitive",
        "resolved": "10.0.0",
        "contentHash": "FU/IfjDfwaMuKr414SSQNTIti/69bHEMb+QKrskRb26oVqpx3lNFXMjs/RC9ZUuhBhcwDM2BwOgoMw+PZ+beqQ==",
        "dependencies": {
          "Microsoft.Extensions.DependencyInjection.Abstractions": "10.0.0",
          "System.Diagnostics.DiagnosticSource": "10.0.0"
        }
      },
      "Microsoft.Extensions.Options": {
        "type": "Transitive",
        "resolved": "10.0.0",
        "contentHash": "8oCAgXOow5XDrY9HaXX1QmH3ORsyZO/ANVHBlhLyCeWTH5Sg4UuqZeOTWJi6484M+LqSx0RqQXDJtdYy2BNiLQ==",
        "dependencies": {
          "Microsoft.Extensions.DependencyInjection.Abstractions": "10.0.0",
          "Microsoft.Extensions.Primitives": "10.0.0"
        }
      },
      "Microsoft.Extensions.Primitives": {
        "type": "Transitive",
        "resolved": "10.0.0",
        "contentHash": "inRnbpCS0nwO/RuoZIAqxQUuyjaknOOnCEZB55KSMMjRhl0RQDttSmLSGsUJN3RQ3ocf5NDLFd2mOQViHqMK5w=="
      },
      "SQLitePCLRaw.bundle_e_sqlite3": {
        "type": "Transitive",
        "resolved": "2.1.11",
        "contentHash": "DC4nA7yWnf4UZdgJDF+9Mus4/cb0Y3Sfgi3gDnAoKNAIBwzkskNAbNbyu+u4atT0ruVlZNJfwZmwiEwE5oz9LQ==",
        "dependencies": {
          "SQLitePCLRaw.lib.e_sqlite3": "2.1.11",
          "SQLitePCLRaw.provider.e_sqlite3": "2.1.11"
        }
      },
      "SQLitePCLRaw.core": {
        "type": "Transitive",
        "resolved": "2.1.11",
        "contentHash": "PK0GLFkfhZzLQeR3PJf71FmhtHox+U3vcY6ZtswoMjrefkB9k6ErNJEnwXqc5KgXDSjige2XXrezqS39gkpQKA==",
        "dependencies": {
          "System.Memory": "4.5.3"
        }
      },
      "SQLitePCLRaw.lib.e_sqlite3": {
        "type": "Transitive",
        "resolved": "2.1.11",
        "contentHash": "Ev2ytaXiOlWZ4b3R67GZBsemTINslLD1DCJr2xiacpn4tbapu0Q4dHEzSvZSMnVWeE5nlObU3VZN2p81q3XOYQ=="
      },
      "SQLitePCLRaw.provider.e_sqlite3": {
        "type": "Transitive",
        "resolved": "2.1.11",
        "contentHash": "Y/0ZkR+r0Cg3DQFuCl1RBnv/tmxpIZRU3HUvelPw6MVaKHwYYR8YNvgs0vuNuXCMvlyJ+Fh88U1D4tah1tt6qw==",
        "dependencies": {
          "SQLitePCLRaw.core": "2.1.11"
        }
      },
      "System.Diagnostics.DiagnosticSource": {
        "type": "Transitive",
        "resolved": "10.0.0",
        "contentHash": "0KdBK+h7G13PuOSC2R/DalAoFMvdYMznvGRuICtkdcUMXgl/gYXsG6z4yUvTxHSMACorWgHCU1Faq0KUHU6yAQ=="
      },
      "System.Memory": {
        "type": "Transitive",
        "resolved": "4.5.3",
        "contentHash": "3oDzvc/zzetpTKWMShs1AADwZjQ/36HnsufHRPcOjyRAAMLDlu2iD33MBI2opxnezcVUtXyqDXXjoFMOU9c7SA=="
      },
      "Omnius.Core.Base": {
        "type": "Project",
        "dependencies": {
          "Microsoft.Extensions.Logging": "[10.0.0, )",
          "NeoSmart.AsyncLock": "[3.2.1, )",
          "System.IO.Pipelines": "[10.0.0, )"
        }
      },
      "Omnius.Core.Collections": {
        "type": "Project",
        "dependencies": {
          "Omnius.Core.Base": "[1.0.0, )"
        }
      },
      "Omnius.Core.Pipelines": {
        "type": "Project",
        "dependencies": {
          "Omnius.Core.Base": "[1.0.0, )"
        }
      },
      "Omnius.Core.RocketPack": {
        "type": "Project",
        "dependencies": {
          "Omnius.Core.Base": "[1.0.0, )",
          "Omnius.Core.Collections": "[1.0.0, )",
          "Omnius.Core.Pipelines": "[1.0.0, )"
        }
      },
      "Omnius.Core.Serialization": {
        "type": "Project",
        "dependencies": {
          "Newtonsoft.Json": "[13.0.4, )",
          "YamlDotNet": "[16.3.0, )"
        }
      },
      "Omnius.Core.Sql": {
        "type": "Project",
        "dependencies": {
          "Omnius.Core.Base": "[1.0.0, )"
        }
      },
      "Omnius.Core.Streams": {
        "type": "Project",
        "dependencies": {
          "Omnius.Core.Base": "[1.0.0, )",
          "Omnius.Core.RocketPack": "[1.0.0, )",
          "Omnius.Core.Serialization": "[1.0.0, )"
        }
      },
      "Microsoft.Extensions.DependencyInjection": {
        "type": "CentralTransitive",
        "requested": "[9.0.5, )",
        "resolved": "10.0.0",
        "contentHash": "f0RBabswJq+gRu5a+hWIobrLWiUYPKMhCD9WO3sYBAdSy3FFH14LMvLVFZc2kPSCimBLxSuitUhsd6tb0TAY6A==",
        "dependencies": {
          "Microsoft.Extensions.DependencyInjection.Abstractions": "10.0.0"
        }
      },
      "Microsoft.Extensions.Logging": {
        "type": "CentralTransitive",
        "requested": "[10.0.0, )",
        "resolved": "10.0.0",
        "contentHash": "BStFkd5CcnEtarlcgYDBcFzGYCuuNMzPs02wN3WBsOFoYIEmYoUdAiU+au6opzoqfTYJsMTW00AeqDdnXH2CvA==",
        "dependencies": {
          "Microsoft.Extensions.DependencyInjection": "10.0.0",
          "Microsoft.Extensions.Logging.Abstractions": "10.0.0",
          "Microsoft.Extensions.Options": "10.0.0"
        }
      },
      "NeoSmart.AsyncLock": {
        "type": "CentralTransitive",
        "requested": "[3.2.1, )",
        "resolved": "3.2.1",
        "contentHash": "bYIpqtgA5oZWdSgcsGA4XLkKVYuz6Qc+aEVfTYPOIX2rSFbb8NFxHcBb5V62qio8Q6Au/Xn+7ci86VW9vqIk0w=="
      },
      "Newtonsoft.Json": {
        "type": "CentralTransitive",
        "requested": "[13.0.4, )",
        "resolved": "13.0.4",
        "contentHash": "pdgNNMai3zv51W5aq268sujXUyx7SNdE2bj1wZcWjAQrKMFZV260lbqYop1d2GM67JI1huLRwxo9ZqnfF/lC6A=="
      },
      "System.IO.Pipelines": {
        "type": "CentralTransitive",
        "requested": "[10.0.0, )",
        "resolved": "10.0.0",
        "contentHash": "M1eb3nfXntaRJPrrMVM9EFS8I1bDTnt0uvUS6QP/SicZf/ZZjydMD5NiXxfmwW/uQwaMDP/yX2P+zQN1NBHChg=="
      },
      "YamlDotNet": {
        "type": "CentralTransitive",
        "requested": "[16.3.0, )",
        "resolved": "16.3.0",
        "contentHash": "SgMOdxbz8X65z8hraIs6hOEdnkH6hESTAIUa7viEngHOYaH+6q5XJmwr1+yb9vJpNQ19hCQY69xbFsLtXpobQA=="
      }
    }
  }
}